mysite/__init__.py
mysite/asgi.py
mysite/settings.py
mysite/urls.py
mysite/wsgi.py
polls/__init__.py
polls/admin.py
polls/apps.py
polls/models.py
polls/tests.py
polls/urls.py
polls/views.py
django_tutorial_gs377209-0.0.3.dist-info/LICENSE
django_tutorial_gs377209-0.0.3.dist-info/METADATA
django_tutorial_gs377209-0.0.3.dist-info/WHEEL
django_tutorial_gs377209-0.0.3.dist-info/top_level.txt
django_tutorial_gs377209-0.0.3.dist-info/RECORD
