Metadata-Version: 2.2
Name: django-tutorial-gs377209
Version: 0.0.3
Summary: A Django app to conduct web-based polls.
Author-email: Gerrod Schirtzinger <gerrod.l.schirtzinger@gmail.com>
Project-URL: Homepage, https://github.com/gs377209/djangotutorial/
Project-URL: Issues, https://github.com/gs377209/djangotutorial/issues
Classifier: Environment :: Web Environment
Classifier: Framework :: Django
Classifier: Framework :: Django :: 5.1
Classifier: Intended Audience :: Developers
Classifier: License :: OSI Approved :: BSD License
Classifier: Operating System :: OS Independent
Classifier: Programming Language :: Python
Classifier: Programming Language :: Python :: 3
Classifier: Programming Language :: Python :: 3 :: Only
Classifier: Programming Language :: Python :: 3.10
Classifier: Programming Language :: Python :: 3.11
Classifier: Programming Language :: Python :: 3.12
Classifier: Programming Language :: Python :: 3.13
Classifier: Topic :: Internet :: WWW/HTTP
Classifier: Topic :: Internet :: WWW/HTTP :: Dynamic Content
Requires-Python: >=3.10
License-File: LICENSE
Requires-Dist: django>=5.1
Requires-Dist: django-debug-toolbar>=5.0.1
Requires-Dist: psycopg2>=2.9.10
Requires-Dist: gunicorn>=23.0.0
Requires-Dist: whitenoise>=6.9.0
Requires-Dist: psycopg>=3.2.5
Provides-Extra: dev
Requires-Dist: flake8>=7.1.2; extra == "dev"
Requires-Dist: pylint; extra == "dev"
Requires-Dist: pytest>=8.3.4; extra == "dev"
Requires-Dist: autopep8>=2.3.2; extra == "dev"
Requires-Dist: pylint-django>=2.6.1; extra == "dev"
Requires-Dist: build>=1.2.2; extra == "dev"
Requires-Dist: twine>=6.1.0; extra == "dev"
